localrec/__init__.py
localrec/bibtex.py
localrec/constants.py
localrec/convert.py
localrec/localrec_logo.png
localrec/progressbar.py
localrec/protocols.conf
localrec/utils.py
localrec/protocols/__init__.py
localrec/protocols/protocol_extract_coordinates_from_subparticles.py
localrec/protocols/protocol_filter_subparticles.py
localrec/protocols/protocol_localized.py
localrec/protocols/protocol_localized_extraction.py
localrec/protocols/protocol_localized_set_origin.py
localrec/protocols/protocol_localized_stitch.py
localrec/protocols/protocol_localized_subset.py
localrec/tests/__init__.py
localrec/tests/test_protocol_localized_reconstruction.py
localrec/viewers/__init__.py
localrec/viewers/viewer.py
scipion_em_localrec-3.2.0.dist-info/LICENCE
scipion_em_localrec-3.2.0.dist-info/METADATA
scipion_em_localrec-3.2.0.dist-info/WHEEL
scipion_em_localrec-3.2.0.dist-info/entry_points.txt
scipion_em_localrec-3.2.0.dist-info/top_level.txt
scipion_em_localrec-3.2.0.dist-info/RECORD
