Metadata-Version: 2.1
Name: scipion-em-localrec
Version: 3.2.0
Summary: Localrec ready to use in scipion.
Home-page: https://github.com/scipion-em/scipion-em-localrec
Author: Laboratory of Structural Biology
Author-email: grp-lsb-software@helsinki.fi
License: UNKNOWN
Keywords: localizedreconstruction cryoem imageprocessing scipion-3.0
Platform: UNKNOWN
